{"story":{"group_1":[{"autoTurnLast":0.01,"bg":"black","bgm":"stop","item":[{"path":"resource/scenario/img/scene0/scene_bg.jpg","posX":0,"posY":0,"visible":"appear","zOrder":"charaBack"},{"path":"resource/scenario/img/scene0/scene_08.png","posX":0,"posY":0,"visible":"appear","zOrder":"charaFront"}],"turnChangeIn":"fadeIn"},{"autoTurnLast":1.0,"turnChangeOut":"fadeOut"},{"autoTurnLast":0.5,"item":[{"path":"resource/scenario/img/scene0/scene_08.png","visible":"hide"}]},{"autoTurnLast":1.5,"item":[{"path":"resource/scenario/img/scene0/scene_10.png","posX":0,"posY":0,"visible":"appear","zOrder":"charaFront"}]},{"autoTurnLast":0.2,"bg":"bg_adv_20191.jpg","chara":[{"cheek":0,"eyeClose":1,"face":"mtn_ex_010.exp3.json","id":200912,"motion":0,"pos":1}],"item":[{"anchor":"skip","path":"resource/scenario/img/scene0/calender_day10.png","posX":-4,"posY":-50,"visible":"appear","zOrder":"messageFront"}],"turnChangeIn":"fadeIn"},{"bgm":"bgm01_anime02","chara":[{"eyeClose":1,"id":200912,"voiceFullAuto":"fullvoice/section_104201/vo_full_902110-030-1"}],"nameAvCenter":"Mabayu","textAvCenter":"[fontSize:20]Phew...","textAvColor":"textMabayu","turnChangeOut":"fadeOut"},{"chara":[{"eyeClose":1,"id":200912,"voiceFullAuto":"fullvoice/section_104201/vo_full_902110-030-2"}],"nameAvCenter":"Mabayu","textAvCenter":"[fontSize:20]Nothing beats a nap during class...@Human experience at its peak."},{"nameAvRight":"Voice from Ground Level","textAvColor":"255255255","textAvRight":"[fontSize:20]Take your places. Get set―!","voiceFullAuto":"fullvoice/section_104201/vo_full_902110-030-3"},{"autoTurnLast":1.2,"nameNarration":"","narration":"[surround:8011_blankgun]*BANG*","narrationEffect":"in","textAvClear":1},{"chara":[{"eyeClose":1,"id":200912,"voiceFullAuto":"fullvoice/section_104201/vo_full_902110-030-4"}],"nameAvCenter":"Mabayu","narrationEffect":"out","textAvCenter":"[fontSize:20]Ah. The endurance test...@Best of luck, peasants.","textAvColor":"textMabayu"},{"chara":[{"eyeClose":1,"id":200912,"motion":200,"voiceFullAuto":"fullvoice/section_104201/vo_full_902110-030-5"}],"nameAvCenter":"Mabayu","textAvCenter":"[fontSize:20]Meanwhile, I'll be up here...@feeling the breeze."},{"chara":[{"eyeClose":1,"id":200912,"voiceFullAuto":"fullvoice/section_104201/vo_full_902110-030-6"}],"nameAvCenter":"Mabayu","textAvCenter":"[fontSize:20]Studying? Running?@Under a blue sky like this? Please."},{"chara":[{"cheek":0,"eyeClose":0,"face":"mtn_ex_020.exp3.json","id":200912,"motion":400,"voiceFullAuto":"fullvoice/section_104201/vo_full_902110-030-7"}],"nameAvCenter":"Mabayu","textAvCenter":"[fontSize:20]Minimum attendance!"},{"chara":[{"id":200912,"voiceFullAuto":"fullvoice/section_104201/vo_full_902110-030-8"}],"nameAvCenter":"Mabayu","textAvCenter":"[fontSize:20]Barely passing grades!@A diploma by the skin of my teeth!"},{"chara":[{"cheek":0,"eyeClose":1,"face":"mtn_ex_010.exp3.json","id":200912,"motion":200,"voiceFullAuto":"fullvoice/section_104201/vo_full_902110-030-9"}],"nameAvCenter":"Mabayu","textAvCenter":"[fontSize:20]That's the dream, baby."},{"chara":[{"eyeClose":1,"id":200912,"lipSynch":0,"voiceFullAuto":"fullvoice/section_104201/vo_full_902110-030-10"}],"nameAvCenter":"Mabayu","textAvCenter":"[fontSize:20]......"},{"autoTurnLast":0.2,"chara":[{"effect":"fadeout","id":200912}],"textAvClear":1},{"chara":[{"cheek":0,"face":"mtn_ex_000.exp3.json","id":200902,"motion":1,"pos":1,"voiceFullAuto":"fullvoice/section_104201/vo_full_902110-030-11"}],"nameAvCenter":"Mabayu","textAvCenter":"[fontSize:20]Still..."},{"chara":[{"id":200902,"voiceFullAuto":"fullvoice/section_104201/vo_full_902110-030-12"}],"nameAvCenter":"Mabayu","textAvCenter":"[fontSize:20]Lately things have been really off..."},{"chara":[{"id":200902,"voiceFullAuto":"fullvoice/section_104201/vo_full_902110-030-13"}],"nameAvCenter":"Mabayu","textAvCenter":"[fontSize:20]Like, the whole world. More than usual.@Am I missing something?"},{"chara":[{"id":200902,"motion":300,"voiceFullAuto":"fullvoice/section_104201/vo_full_902110-030-14"}],"nameAvCenter":"Mabayu","textAvCenter":"[fontSize:20]I mean, factory explosions?@Amy coming back to life?"},{"chara":[{"cheek":0,"face":"mtn_ex_030.exp3.json","id":200902,"voiceFullAuto":"fullvoice/section_104201/vo_full_902110-030-15"}],"nameAvCenter":"Mabayu","textAvCenter":"[fontSize:20]And to top it off, time literally stopping?@It doesn't make sense..."},{"chara":[{"cheek":0,"face":"mtn_ex_040.exp3.json","id":200902,"motion":200,"voiceFullAuto":"fullvoice/section_104201/vo_full_902110-030-16"}],"nameAvCenter":"Mabayu","textAvCenter":"[fontSize:20]And I can't control it! If I'm gonna get dragged@into the supernatural, at least give me powers..."},{"chara":[{"eyeClose":1,"id":200902,"voiceFullAuto":"fullvoice/section_104201/vo_full_902110-030-17"}],"nameAvCenter":"Mabayu","textAvCenter":"[fontSize:20]*Sigh*"},{"chara":[{"eyeClose":1,"id":200902,"lipSynch":0,"voiceFullAuto":"fullvoice/section_104201/vo_full_902110-030-18"}],"nameAvCenter":"Mabayu","textAvCenter":"[fontSize:20]......"},{"chara":[{"cheek":0,"eyeClose":0,"face":"mtn_ex_000.exp3.json","id":200902,"lipSynch":1,"motion":100,"voiceFullAuto":"fullvoice/section_104201/vo_full_902110-030-19"}],"nameAvCenter":"Mabayu","textAvCenter":"[fontSize:20]Okay, enough moping.@Let's try thinking positive."},{"chara":[{"cheek":0,"face":"mtn_ex_020.exp3.json","id":200902,"motion":400,"voiceFullAuto":"fullvoice/section_104201/vo_full_902110-030-20"}],"nameAvCenter":"Mabayu","textAvCenter":"[fontSize:20]Even if I can't control the time-stopping junk,@the fact that it's happening is amazing!"},{"chara":[{"id":200902,"voiceFullAuto":"fullvoice/section_104201/vo_full_902110-030-21"}],"nameAvCenter":"Mabayu","textAvCenter":"[fontSize:20]It's a superpower!@So the next time it happens..."},{"chara":[{"cheek":0,"face":"mtn_ex_000.exp3.json","id":200902,"motion":0,"voiceFullAuto":"fullvoice/section_104201/vo_full_902110-030-22"}],"nameAvCenter":"Mabayu","textAvCenter":"[fontSize:20]I'll do something big!"},{"chara":[{"cheek":0,"face":"mtn_ex_050.exp3.json","id":200902,"motion":100,"pos":1,"voiceFullAuto":"fullvoice/section_104201/vo_full_902110-030-23"}],"nameAvCenter":"Mabayu","textAvCenter":"[fontSize:20]I'll..."},{"chara":[{"eyeClose":1,"id":200902,"lipSynch":0,"voiceFullAuto":"fullvoice/section_104201/vo_full_902110-030-24"}],"nameAvCenter":"Mabayu","textAvCenter":"[fontSize:20]......"},{"chara":[{"eyeClose":0,"id":200902,"lipSynch":1,"voiceFullAuto":"fullvoice/section_104201/vo_full_902110-030-25"}],"nameAvCenter":"Mabayu","textAvCenter":"[fontSize:20]...Cheat on another quiz?"},{"chara":[{"cheek":0,"face":"mtn_ex_030.exp3.json","id":200902,"motion":300,"pos":1,"voiceFullAuto":"fullvoice/section_104201/vo_full_902110-030-26"}],"nameAvCenter":"Mabayu","textAvCenter":"[fontSize:20]Wow. Inspiring.@My imagination knows no bounds."},{"chara":[{"id":200902,"voiceFullAuto":"fullvoice/section_104201/vo_full_902110-030-27"}],"nameAvCenter":"Mabayu","textAvCenter":"[fontSize:20]Come on, Mabayu. Think bigger!"},{"chara":[{"cheek":0,"eyeClose":1,"face":"mtn_ex_000.exp3.json","id":200902,"motion":1,"voiceFullAuto":"fullvoice/section_104201/vo_full_902110-030-28"}],"nameAvCenter":"Mabayu","textAvCenter":"[fontSize:20]There's gotta be something cooler@I could do with frozen time..."},{"chara":[{"eyeClose":0,"id":200902,"voiceFullAuto":"fullvoice/section_104201/vo_full_902110-030-29"}],"nameAvCenter":"Mabayu","textAvCenter":"[fontSize:20]Like...steal a diamond!"},{"chara":[{"cheek":0,"face":"mtn_ex_030.exp3.json","id":200902,"lipSynch":0,"voiceFullAuto":"fullvoice/section_104201/vo_full_902110-030-30"}],"nameAvCenter":"Mabayu","textAvCenter":"[fontSize:20]......"},{"chara":[{"cheek":0,"face":"mtn_ex_040.exp3.json","id":200902,"lipSynch":1,"motion":100,"voiceFullAuto":"fullvoice/section_104201/vo_full_902110-030-31"}],"nameAvCenter":"Mabayu","textAvCenter":"[fontSize:20]Am I just...lame? What kind of person gets time@stops and still can't do anything interesting?"},{"bgEffect":"shakeSmall","nameAvRight":"Voice from Ground Level","textAvColor":"textHomura","textAvRight":"[fontSize:20]*Shriek*","voiceFullAuto":"fullvoice/section_104201/vo_full_902110-030-32"},{"chara":[{"cheek":0,"face":"mtn_ex_050.exp3.json","id":200902,"lipSynch":0,"motion":0,"voiceFullAuto":"fullvoice/section_104201/vo_full_902110-030-33"}],"nameAvCenter":"Mabayu","textAvCenter":"[fontSize:20]......Hm?","textAvColor":"textMabayu"},{"chara":[{"id":200902,"lipSynch":1,"voiceFullAuto":"fullvoice/section_104201/vo_full_902110-030-34"}],"nameAvCenter":"Mabayu","textAvCenter":"[fontSize:20]Was that from the field?"},{"autoTurnLast":0.2,"bg":"bg_adv_24012.jpg","item":[{"anchor":"skip","path":"resource/scenario/img/scene0/calender_day10.png","posX":-4,"posY":-50,"visible":"appear","zOrder":"messageFront"}],"textAvClear":1,"turnChangeIn":"rollInFast"},{"nameAvRight":"Voice from Ground Level","textAvColor":"textHomura","textAvRight":"[fontSize:20]Owww...","turnChangeOut":"rollOutFast","voiceFullAuto":"fullvoice/section_104201/vo_full_902110-030-35"},{"nameAvLeft":"Voice from Ground Level","textAvColor":"textMadoka","textAvLeft":"[fontSize:20]Are you all right, Miss Akemi?@Should we go to the nurse?","voiceFullAuto":"fullvoice/section_104201/vo_full_902110-030-36"},{"autoTurnLast":0.2,"bg":"bg_adv_20191.jpg","chara":[{"cheek":0,"face":"mtn_ex_000.exp3.json","id":200912,"motion":1,"pos":1}],"item":[{"anchor":"skip","path":"resource/scenario/img/scene0/calender_day10.png","posX":-4,"posY":-50,"visible":"appear","zOrder":"messageFront"}],"textAvClear":1,"turnChangeIn":"rollInFast"},{"chara":[{"id":200912,"voiceFullAuto":"fullvoice/section_104201/vo_full_902110-030-37"}],"nameAvCenter":"Mabayu","textAvCenter":"[fontSize:20]She missed the mat during her high jump?@Yikes.","textAvColor":"textMabayu","turnChangeOut":"rollOutFast"},{"chara":[{"cheek":0,"face":"mtn_ex_050.exp3.json","id":200912,"voiceFullAuto":"fullvoice/section_104201/vo_full_902110-030-38"}],"nameAvCenter":"Mabayu","textAvCenter":"[fontSize:20]Wait, THAT'S where she landed?@That's...kind of a long way off."},{"chara":[{"cheek":0,"face":"mtn_ex_030.exp3.json","id":200912,"voiceFullAuto":"fullvoice/section_104201/vo_full_902110-030-39"}],"nameAvCenter":"Mabayu","textAvCenter":"[fontSize:20]Geez...someone's healthy."},{"chara":[{"eyeClose":1,"id":200912,"motion":200,"voiceFullAuto":"fullvoice/section_104201/vo_full_902110-030-40"}],"nameAvCenter":"Mabayu","textAvCenter":"[fontSize:20]If she's got energy to burn,@can she lend me a little?"},{"autoTurnLast":2.0,"turnChangeIn":"fadeIn"}]},"version":3}