{"story":{"group_1":[{"autoTurnLast":0.2,"bg":"bg_adv_23051.jpg","chara":[{"cheek":0,"face":"mtn_ex_030.exp3.json","id":200912,"motion":0,"pos":1}],"item":[{"anchor":"skip","path":"resource/scenario/img/scene0/calender_day01.png","posX":-4,"posY":-50,"visible":"appear","zOrder":"messageFront"}],"turnChangeIn":"fadeIn"},{"autoTurnLast":0.1,"bgm":"bgm01_anime02","turnChangeOut":"fadeOut"},{"FnarrationAnchor":"top","FnarrationCoverColor":"textBlack","FnarrationCoverOpacity":110.0,"FnarrationEffect":"in","FnarrationFontSize":18.0,"FnarrationHeight":100.0,"FnarrationLineMargin":30.0,"FnarrationLineSpace":20.0,"FnarrationOutlineColor":"textBlack","FnarrationOutlineWeight":2,"FnarrationTextColor":"textMabayu","FnarrationWidth":310.0,"FnarrationX":220.0,"FnarrationY":-110.0,"chara":[{"eyeClose":1,"id":200912,"lipSynch":0,"motion":300,"voiceFullAuto":"fullvoice/section_104201/vo_full_902101-020-1"}],"nameFnarration":"Mabayu","progressFnarration":"(The sun...it burns.@Eyes. Heavy. Spirit.@Fading...)"},{"chara":[{"eyeClose":1,"id":200912,"lipSynch":0,"voiceFullAuto":"fullvoice/section_104201/vo_full_902101-020-2"}],"progressFnarration":"(I am the night. I work alone.@It's abuse to make@me go to school...)"},{"chara":[{"eyeClose":0,"id":200912,"lipSynch":0,"motion":0,"voiceFullAuto":"fullvoice/section_104201/vo_full_902101-020-3"}],"progressFnarration":"(The second I'm at@my desk, I'm going@back to sleep.)"},{"FnarrationEffect":"out","autoTurnLast":0.1},{"nameAvRight":"Mami's Voice","textAvColor":"textMami","textAvRight":"[fontSize:20]Oh!","voiceFullAuto":"fullvoice/section_104201/vo_full_902101-020-4"},{"autoTurnLast":0.01,"textAvClear":1},{"FnarrationCoverColor":"textBlack","FnarrationCoverOpacity":110.0,"FnarrationEffect":"in","FnarrationFontSize":18.0,"FnarrationHeight":50.0,"FnarrationLineMargin":30.0,"FnarrationLineSpace":20.0,"FnarrationOutlineColor":"textBlack","FnarrationOutlineWeight":2,"FnarrationTextColor":"textMabayu","FnarrationWidth":100.0,"FnarrationX":180.0,"FnarrationY":50.0,"chara":[{"cheek":0,"face":"mtn_ex_050.exp3.json","id":200912,"lipSynch":0,"voiceFullAuto":"fullvoice/section_104201/vo_full_902101-020-5"}],"nameFnarration":"Mabayu","progressFnarration":"(Hm?)","textAvColor":"textMabayu"},{"FnarrationEffect":"out","autoTurnLast":0.5,"chara":[{"effect":"fadeout","id":200912}]},{"chara":[{"cheek":0,"face":"mtn_ex_010.exp3.json","id":200501,"motion":100,"pos":1,"voiceFullAuto":"fullvoice/section_104201/vo_full_902101-020-6"}],"nameAvCenter":"Mami","textAvCenter":"[fontSize:20]Good morning.","textAvColor":"textMami"},{"chara":[{"id":200501,"voiceFullAuto":"fullvoice/section_104201/vo_full_902101-020-6b"}],"nameAvCenter":"Mami","textAvCenter":"[fontSize:20]So, about that book I borrowed yesterday...","textAvColor":"textMami"},{"autoTurnLast":0.01,"textAvClear":1},{"FnarrationCoverColor":"textBlack","FnarrationCoverOpacity":110.0,"FnarrationEffect":"in","FnarrationFontSize":18.0,"FnarrationHeight":100.0,"FnarrationLineMargin":30.0,"FnarrationLineSpace":20.0,"FnarrationOutlineColor":"textBlack","FnarrationOutlineWeight":2,"FnarrationTextColor":"textMabayu","FnarrationWidth":330.0,"FnarrationX":0.0,"FnarrationY":-30.0,"chara":[{"id":200501,"motion":1}],"nameFnarration":"Mabayu","progressFnarration":"(Mami...what's her name.@Tomoe?@Is she in my class?)","textAvColor":"textMabayu","voiceFullAuto":"fullvoice/section_104201/vo_full_902101-020-7"},{"progressFnarration":"(I think so. Probably.)","voiceFullAuto":"fullvoice/section_104201/vo_full_902101-020-8"},{"progressFnarration":"(What does she want?@She comes by our shop for@cake now and then, but...)","voiceFullAuto":"fullvoice/section_104201/vo_full_902101-020-9"},{"FnarrationEffect":"out","autoTurnLast":0.2,"chara":[{"effect":"fadeout","id":200501}]},{"autoTurnLast":0.2,"chara":[{"cheek":0,"face":"mtn_ex_000.exp3.json","id":200912,"motion":0,"pos":1}]},{"FnarrationAnchor":"center","FnarrationCoverColor":"textBlack","FnarrationCoverOpacity":110.0,"FnarrationEffect":"in","FnarrationFontSize":18.0,"FnarrationHeight":125.0,"FnarrationLineMargin":30.0,"FnarrationLineSpace":15.0,"FnarrationOutlineColor":"textBlack","FnarrationOutlineWeight":2,"FnarrationTextColor":"textMabayu","FnarrationWidth":335.0,"FnarrationX":220.0,"FnarrationY":-80.0,"chara":[{"id":200912,"lipSynch":0,"voiceFullAuto":"fullvoice/section_104201/vo_full_902101-020-10"}],"nameFnarration":"Mabayu","progressFnarration":"(We've definitely@never talked.)","textAvColor":"textMabayu"},{"chara":[{"id":200912,"lipSynch":0,"motion":200,"voiceFullAuto":"fullvoice/section_104201/vo_full_902101-020-11"}],"progressFnarration":"(You've got friends you@can borrow books from?@Whoopee for you.)"},{"chara":[{"eyeClose":1,"id":200912,"lipSynch":0,"voiceFullAuto":"fullvoice/section_104201/vo_full_902101-020-12"}],"progressFnarration":"(Now leave me alone.@It's got nothing@to do with me.)"},{"FnarrationEffect":"out","autoTurnLast":1.0,"chara":[{"effect":"fadeout","id":200912}]},{"chara":[{"cheek":0,"face":"mtn_ex_050.exp3.json","id":200501,"lipSynch":0,"motion":0,"pos":1,"voiceFullAuto":"fullvoice/section_104201/vo_full_902101-020-13"}],"nameAvCenter":"Mami","textAvCenter":"[fontSize:20]......?","textAvColor":"textMami"},{"autoTurnLast":2.0,"turnChangeIn":"fadeIn"}]},"version":3}
