{"story":{"group_1":[{"autoTurnLast":0.2,"bg":"bg_adv_20201.jpg","chara":[{"cheek":0,"face":"mtn_ex_030.exp3.json","id":200301,"motion":0,"pos":1}],"item":[{"anchor":"skip","path":"resource/scenario/img/scene0/calender_day10.png","posX":-4,"posY":-50,"visible":"appear","zOrder":"messageFront"}],"turnChangeIn":"fadeIn"},{"autoTurnLast":0.01,"bgm":"bgm01_anime07","turnChangeOut":"fadeOut"},{"FnarrationCoverColor":"textBlack","FnarrationCoverOpacity":110.0,"FnarrationEffect":"in","FnarrationFontSize":18.0,"FnarrationHeight":100.0,"FnarrationLineMargin":30.0,"FnarrationLineSpace":20.0,"FnarrationOutlineColor":"textBlack","FnarrationOutlineWeight":2,"FnarrationTextColor":"textHomura","FnarrationWidth":335.0,"FnarrationX":-220.0,"FnarrationY":150.0,"chara":[{"eyeClose":1,"id":200301}],"nameFnarration":"Homura","progressFnarration":"(*Sigh*...@I really messed up.)","textAvColor":"textHomura"},{"chara":[{"eyeClose":1,"id":200301}],"progressFnarration":"(Why did I even mention \"Magical@Girls\" in front of everyone?)"},{"chara":[{"cheek":0,"eyeClose":0,"face":"mtn_ex_040.exp3.json","id":200301,"motion":100}],"progressFnarration":"(Miss Kaname isn't how@I remember her, either...)"},{"chara":[{"id":200301}],"progressFnarration":"(She seemed rather@unsure of me...)"},{"chara":[{"cheek":0,"face":"mtn_ex_030.exp3.json","id":200301}],"progressFnarration":"(Well, I guess that's only natural.@This is her first time@meeting me.)"},{"chara":[{"id":200301,"motion":0}],"progressFnarration":"(But... The Miss Kaname I knew@really is gone.)"},{"chara":[{"eyeClose":1,"id":200301}],"progressFnarration":"(It feels...lonelier than@I expected.)"},{"FnarrationEffect":"out","autoTurnLast":0.2,"chara":[{"effect":"fadeout","id":200301}]},{"chara":[{"cheek":0,"face":"mtn_ex_010.exp3.json","id":800700,"motion":0,"pos":1}],"nameAvCenter":"Teacher","textAvCenter":"[fontSize:20]Homura Akemi.","textAvColorRGB":"255255255"},{"autoTurnLast":0.2,"chara":[{"id":800700,"pos":0}],"textAvClear":1},{"chara":[{"cheek":0,"face":"mtn_ex_050.exp3.json","id":200301,"motion":400,"pos":2}],"nameAvRight":"Homura","textAvColor":"textHomura","textAvRight":"[fontSize:20]Y...Yes."},{"chara":[{"id":800700}],"nameAvLeft":"Teacher","textAvColorRGB":"255255255","textAvLeft":"[fontSize:20]All right, why don't you@try solving this one?"},{"chara":[{"id":200301,"lipSynch":0,"motion":0}],"nameAvRight":"Homura","textAvColor":"textHomura","textAvRight":"[fontSize:20]......"},{"autoTurnLast":0.2,"chara":[{"effect":"fadeout","id":800700}],"textAvClear":1},{"autoTurnLast":0.2,"chara":[{"id":200301,"pos":1}]},{"FnarrationCoverColor":"textBlack","FnarrationCoverOpacity":110.0,"FnarrationEffect":"in","FnarrationFontSize":18.0,"FnarrationHeight":100.0,"FnarrationLineMargin":30.0,"FnarrationLineSpace":20.0,"FnarrationOutlineColor":"textBlack","FnarrationOutlineWeight":2,"FnarrationTextColor":"textHomura","FnarrationWidth":300.0,"FnarrationX":-220.0,"FnarrationY":150.0,"chara":[{"id":200301}],"nameFnarration":"Homura","progressFnarration":"(Um, how did this@problem go...?)","textAvColor":"textHomura"},{"FnarrationEffect":"out","autoTurnLast":0.01},{"autoTurnLast":2.5,"chara":[{"cheek":0,"face":"mtn_ex_040.exp3.json","id":200301,"lipSynch":0}],"nameAvCenter":"Homura","textAvCenter":"[fontSize:20][surround:8068_blackboardwriting]......","textAvColor":"textHomura"},{"chara":[{"cheek":0,"face":"mtn_ex_010.exp3.json","id":200301,"lipSynch":1,"motion":100}],"nameAvCenter":"Homura","surround":"stop","textAvCenter":"[fontSize:20]All done!","textAvColor":"textHomura"},{"autoTurnLast":0.2,"chara":[{"id":200301,"pos":2}],"textAvClear":1},{"chara":[{"cheek":0,"face":"mtn_ex_050.exp3.json","id":800700,"motion":0,"pos":0}],"nameAvLeft":"Teacher","textAvColorRGB":"255255255","textAvLeft":"[fontSize:20]Oh, that was fast."},{"chara":[{"cheek":0,"face":"mtn_ex_010.exp3.json","id":800700}],"nameAvLeft":"Teacher","textAvColorRGB":"255255255","textAvLeft":"[fontSize:20]Looks correct. You were out@sick for a while, weren't you?"},{"chara":[{"id":200301,"motion":1}],"nameAvRight":"Homura","textAvColor":"textHomura","textAvRight":"[fontSize:20]I had plenty of time to study@while in the hospital."},{"autoTurnLast":0.2,"chara":[{"effect":"fadeout","id":800700}],"textAvClear":1},{"autoTurnLast":0.2,"chara":[{"id":200301,"pos":1}]},{"FnarrationCoverColor":"textBlack","FnarrationCoverOpacity":110.0,"FnarrationEffect":"in","FnarrationFontSize":18.0,"FnarrationHeight":100.0,"FnarrationLineMargin":30.0,"FnarrationLineSpace":20.0,"FnarrationOutlineColor":"textBlack","FnarrationOutlineWeight":2,"FnarrationTextColor":"textHomura","FnarrationWidth":340.0,"FnarrationX":-220.0,"FnarrationY":150.0,"chara":[{"eyeClose":1,"id":200301}],"nameFnarration":"Homura","progressFnarration":"(It'll be okay. This is different@from last time.)","textAvColor":"textHomura"},{"chara":[{"eyeClose":1,"id":200301}],"progressFnarration":"(Even if her memory is gone...)"},{"chara":[{"eyeClose":0,"id":200301,"motion":0}],"progressFnarration":"(I still remember her!)"},{"chara":[{"cheek":0,"face":"mtn_ex_020.exp3.json","id":200301,"motion":200}],"progressFnarration":"(I'll save Miss Kaname, and this time@we'll defeat Walpurgisnacht.)"},{"FnarrationEffect":"out","autoTurnLast":2.0,"turnChangeIn":"fadeIn"}]},"version":3}
