{"story":{"group_1":[{"autoTurnLast":0.01,"bg":"bg_adv_14134.jpg","bgm":"bgm03_story12","chara":[{"cheek":0,"face":"mtn_ex_020.exp3.json","id":102100,"motion":1,"pos":1}],"turnChangeIn":"fadeIn"},{"autoTurnLast":2.0,"turnChangeOut":"fadeOut"},{"autoTurnLast":0.1,"chara":[{"effect":"fadeout","id":102100}],"textClear":1},{"autoTurnLast":0.1,"bg":"bg_adv_14134.jpg","bgChangeEffect":"cameraPan"},{"autoTurnLast":2.5,"chara":[{"cheek":0,"eyeClose":1,"face":"mtn_ex_001.exp3.json","id":102500,"motion":200,"pos":1}],"textClear":1},{"autoTurnLast":0.1,"chara":[{"effect":"fadeout","id":102500}],"textClear":1},{"autoTurnLast":0.1,"bg":"bg_adv_14134.jpg","bgChangeEffect":"cameraPan"},{"autoTurnLast":2.0,"chara":[{"cheek":0,"eyeClose":1,"face":"mtn_ex_030.exp3.json","id":102800,"motion":1,"pos":1}],"textClear":1},{"autoTurnLast":0.1,"chara":[{"effect":"fadeout","id":102800}],"textClear":1},{"autoTurnLast":0.1,"bg":"bg_adv_14134.jpg","bgChangeEffect":"cameraPan"},{"autoTurnLast":2.0,"chara":[{"cheek":0,"face":"mtn_ex_000.exp3.json","id":103300,"motion":0,"pos":1}],"textClear":1},{"autoTurnLast":0.1,"chara":[{"effect":"fadeout","id":103300}],"textClear":1},{"autoTurnLast":0.1,"bg":"bg_adv_14134.jpg","bgChangeEffect":"cameraPan"},{"chara":[{"cheek":0,"face":"mtn_ex_030.exp3.json","id":100100,"lipSynch":0,"motion":0,"pos":1,"voiceFullAuto":"fullvoice/section_103204/vo_full_103204-4-1"}],"nameCenter":"Iroha","textCenter":"..."},{"chara":[{"eyeClose":1,"id":100100,"motion":1}],"nameNarration":"Iroha","narration":"I sent a message to all of our Magical Girls,@but there's been no response,@not even a \"read\" indicator.","narrationBg":"","narrationEffect":"in","voiceFullAuto":"fullvoice/section_103204/vo_full_103204-4-2"},{"narration":"It seems clear that every Magical Girl in Kamihama,@even the ones who didn't come here with us,@are in a world of nightmares...","voiceFullAuto":"fullvoice/section_103204/vo_full_103204-4-3"},{"chara":[{"id":100100,"motion":300}],"narration":"Even if we try to use the power of Magical Girls,@we only have access to our own.","voiceFullAuto":"fullvoice/section_103204/vo_full_103204-4-4"},{"narration":"Even if we try to find the core that Kyubey@has hidden, we could be too late to stop@everyone from turning into Witches in the meantime.","voiceFullAuto":"fullvoice/section_103204/vo_full_103204-4-5"},{"chara":[{"id":100100,"motion":200}],"narration":"But even so, if all we're doing is thinking in circles@without coming to a solution, then maybe we would@have been better off searching for the core@instead of doing nothing...","voiceFullAuto":"fullvoice/section_103204/vo_full_103204-4-6"},{"chara":[{"cheek":1,"eyeClose":0,"face":"mtn_ex_031.exp3.json","id":100100,"motion":0}],"narration":"It's no good...","voiceFullAuto":"fullvoice/section_103204/vo_full_103204-4-7"},{"narration":"The more I try to think about it,@the more anxious I get...@And the more anxious I get, the more my thoughts@turn to useless ideas, like how this all happened...","voiceFullAuto":"fullvoice/section_103204/vo_full_103204-4-8"},{"chara":[{"eyeClose":1,"id":100100,"motion":100}],"narration":"It's not Himena's fault...@Kyubey said that he had nothing to do with it...@So then...what brought this about...?","voiceFullAuto":"fullvoice/section_103204/vo_full_103204-4-9"},{"chara":[{"id":100100}],"narration":"Why is everyone on the verge@of turning into Witches...?","voiceFullAuto":"fullvoice/section_103204/vo_full_103204-4-10"},{"autoTurnLast":0.1,"narrationEffect":"out"},{"chara":[{"id":100100,"lipSynch":0,"motion":301,"tear":1,"voiceFullAuto":"fullvoice/section_103204/vo_full_103204-4-11"}],"nameCenter":"Iroha","textCenter":"..."},{"chara":[{"eyeClose":1,"id":100100,"lipSynch":0,"voiceFullAuto":"fullvoice/section_103204/vo_full_103204-4-12"}],"nameCenter":"Iroha","textCenter":"(Just as I thought...I...)"},{"autoTurnLast":0.01,"bg":"black","turnChangeIn":"fadeIn"},{"nameNarration":"Iroha","narration":"It feels like I haven't been able to make any@of the grand ideals I spoke of come true...","narrationBg":"black","narrationEffect":"in","turnChangeOut":"fadeOut","voiceFullAuto":"fullvoice/section_103204/vo_full_103204-4-13"},{"narration":"But...","voiceFullAuto":"fullvoice/section_103204/vo_full_103204-4-14"},{"autoTurnLast":2.0,"bg":"bg_adv_11041.jpg","chara":[{"cheek":0,"face":"mtn_ex_010.exp3.json","id":100101,"motion":301,"pos":1}],"narrationEffect":"out","turnChangeIn":"fadeIn","turnEffect":"blackFrame"},{"chara":[{"cheek":0,"face":"mtn_ex_010.exp3.json","id":100101,"voiceFullAuto":"fullvoice/section_103204/vo_full_103204-4-15"}],"nameCenter":"Iroha","textCenter":"We'd worry less about being@Magical Girls than we do now.","turnChangeOut":"fadeOut"},{"chara":[{"eyeClose":1,"id":100101,"voiceFullAuto":"fullvoice/section_103204/vo_full_103204-4-16"}],"nameCenter":"Iroha","textCenter":"We'd be able to live long enough@to fulfill our dreams for the future."},{"chara":[{"eyeClose":0,"id":100101,"motion":200,"voiceFullAuto":"fullvoice/section_103204/vo_full_103204-4-17"}],"nameCenter":"Iroha","textCenter":"We'd be able to tell people about the fate we bear,@and why we made our wishes."},{"chara":[{"cheek":0,"face":"mtn_ex_011.exp3.json","id":100101,"voiceFullAuto":"fullvoice/section_103204/vo_full_103204-4-18"}],"nameCenter":"Iroha","textCenter":"And I hope that we, and everyone around us,@will become kinder bit by bit."},{"chara":[{"cheek":0,"face":"mtn_ex_050.exp3.json","id":100101,"motion":1,"voiceFullAuto":"fullvoice/section_103204/vo_full_103204-4-19"}],"nameCenter":"Iroha","textCenter":"Mmm, I guess what I'm wondering is,"},{"chara":[{"id":100101,"voiceFullAuto":"fullvoice/section_103204/vo_full_103204-4-20"}],"nameCenter":"Iroha","textCenter":"if we can work to resolve the hardships@of the present, and at the same time,"},{"chara":[{"id":100101,"motion":100,"voiceFullAuto":"fullvoice/section_103204/vo_full_103204-4-21"}],"nameCenter":"Iroha","textCenter":"gradually sow the seeds of kindness in@everyone to ward off future hardships...?"},{"chara":[{"id":100101,"voiceFullAuto":"fullvoice/section_103204/vo_full_103204-4-22"}],"nameCenter":"Iroha","textCenter":"Wouldn't it be nice if we could do that...?"},{"autoTurnLast":0.5,"chara":[{"cheek":0,"face":"mtn_ex_040.exp3.json","id":102801,"motion":1,"pos":1}],"turnChangeIn":"fadeIn"},{"chara":[{"id":102801,"voiceFullAuto":"fullvoice/section_103204/vo_full_103204-4-23"}],"nameCenter":"Himena","textCenter":"What Irorin and everyone's doing@sounds kind and all, but...","turnChangeOut":"fadeOut"},{"chara":[{"cheek":0,"face":"mtn_ex_030.exp3.json","id":102801,"voiceFullAuto":"fullvoice/section_103204/vo_full_103204-4-24"}],"nameCenter":"Himena","textCenter":"it's actually a really hard thing to do,@we're talking super macho, it's crazy."},{"chara":[{"cheek":0,"face":"mtn_ex_010.exp3.json","id":102801,"motion":100,"voiceFullAuto":"fullvoice/section_103204/vo_full_103204-4-25"}],"nameCenter":"Himena","textCenter":"So that's why, for all the girls that can't keep up@and have become Feathers in their pain,"},{"chara":[{"cheek":0,"face":"mtn_ex_011.exp3.json","id":102801,"voiceFullAuto":"fullvoice/section_103204/vo_full_103204-4-26"}],"nameCenter":"Himena","textCenter":"this cutie and her fellows will take care of them★"},{"autoTurnLast":0.5,"chara":[{"cheek":0,"face":"mtn_ex_000.exp3.json","id":102101,"motion":0,"pos":1}],"turnChangeIn":"fadeIn"},{"chara":[{"id":102101,"motion":100,"voiceFullAuto":"fullvoice/section_103204/vo_full_103204-4-27"}],"nameCenter":"Yuna","textCenter":"I'd like for Futatsugi to continue@on without conflict forever.","turnChangeOut":"fadeOut"},{"chara":[{"cheek":0,"face":"mtn_ex_010.exp3.json","id":102101,"voiceFullAuto":"fullvoice/section_103204/vo_full_103204-4-28"}],"nameCenter":"Yuna","textCenter":"So, fundamentally, I'd say I'm@the same case as Tamaki."},{"autoTurnLast":0.5,"chara":[{"cheek":0,"face":"mtn_ex_011.exp3.json","id":102501,"motion":0,"pos":1}],"turnChangeIn":"fadeIn"},{"chara":[{"id":102501,"motion":100,"voiceFullAuto":"fullvoice/section_103204/vo_full_103204-4-29"}],"nameCenter":"Shizuka","textCenter":"Peace and prosperity in the Land of the Rising Sun!@That's all!","turnChangeOut":"fadeOut"},{"chara":[{"cheek":0,"face":"mtn_ex_001.exp3.json","id":102501,"voiceFullAuto":"fullvoice/section_103204/vo_full_103204-4-30"}],"nameCenter":"Shizuka","textCenter":"Of course, that doesn't mean@that we'd resort to violence!"},{"chara":[{"cheek":0,"face":"mtn_ex_030.exp3.json","id":102501,"motion":200,"voiceFullAuto":"fullvoice/section_103204/vo_full_103204-4-31"}],"nameCenter":"Shizuka","textCenter":"Rather, as a clan we'll support@everyone from behind the scenes."},{"autoTurnLast":2.0,"bg":"bg_adv_14134.jpg","chara":[{"cheek":1,"eyeClose":1,"face":"mtn_ex_030.exp3.json","id":100100,"motion":0,"pos":1}],"turnChangeIn":"fadeIn","turnEffect":"stop"},{"chara":[{"id":100100,"lipSynch":0,"motion":300,"voiceFullAuto":"fullvoice/section_103204/vo_full_103204-4-32"}],"nameCenter":"Iroha","textCenter":"(Ah, I'm so pathetic...)","turnChangeOut":"fadeOut"},{"chara":[{"id":100100,"lipSynch":0,"voiceFullAuto":"fullvoice/section_103204/vo_full_103204-4-33"}],"nameCenter":"Iroha","textCenter":"(Everyone is going through nightmares and@they're on the brink of becoming Witches.)"},{"chara":[{"id":100100,"lipSynch":0,"voiceFullAuto":"fullvoice/section_103204/vo_full_103204-4-34"}],"nameCenter":"Iroha","textCenter":"(While there's still a chance to save them, I'm@getting stuck thinking that it won't work.)"},{"chara":[{"id":100100,"motion":200,"voiceFullAuto":"fullvoice/section_103204/vo_full_103204-4-35"}],"nameCenter":"Iroha","textCenter":"Because I'm too indecisive,@I can't protect anything..."},{"nameNarration":"Iroha","narration":"I'm sorry...@Yachiyo, Tsuruno,@Felicia, Sana, everyone...","narrationBg":"","narrationEffect":"in","voiceFullAuto":"fullvoice/section_103204/vo_full_103204-4-36"},{"autoTurnLast":0.1,"bgm":"stop","narrationEffect":"out"},{"chara":[{"cheek":0,"eyeClose":0,"face":"mtn_ex_021.exp3.json","id":100100,"motion":0,"voiceFullAuto":"fullvoice/section_103204/vo_full_103204-4-37"}],"nameCenter":"Iroha","textCenter":"Let's try it..."},{"autoTurnLast":0.2,"chara":[{"id":100100,"pos":0}],"textClear":1},{"chara":[{"cheek":0,"face":"mtn_ex_050.exp3.json","id":101500,"motion":200,"pos":2,"voiceFullAuto":"fullvoice/section_103204/vo_full_103204-4-38"}],"nameRight":"Ui","textRight":"Sis...?"},{"autoTurnLast":0.2,"chara":[{"effect":"fadeout","id":100100},{"effect":"fadeout","id":101500}],"textClear":1},{"chara":[{"cheek":0,"face":"mtn_ex_050.exp3.json","id":102500,"motion":1,"pos":1,"voiceFullAuto":"fullvoice/section_103204/vo_full_103204-4-39"},{"cheek":0,"face":"mtn_ex_050.exp3.json","id":102100,"motion":0,"pos":0},{"cheek":0,"face":"mtn_ex_050.exp3.json","id":102800,"motion":0,"pos":2}],"nameCenter":"Shizuka","textCenter":"Iroha, have you thought of something?"},{"autoTurnLast":0.2,"chara":[{"effect":"fadeout","id":102500},{"effect":"fadeout","id":102100},{"effect":"fadeout","id":102800}],"textClear":1},{"bgm":"bgm24_story04","chara":[{"cheek":0,"face":"mtn_ex_021.exp3.json","id":100100,"motion":0,"pos":1,"voiceFullAuto":"fullvoice/section_103204/vo_full_103204-4-40"}],"nameCenter":"Iroha","textCenter":"Yeah..."},{"chara":[{"id":100100,"motion":100,"voiceFullAuto":"fullvoice/section_103204/vo_full_103204-4-41"}],"nameCenter":"Iroha","textCenter":"Right here, we have Ui, who used@to be the core of Eve."},{"chara":[{"id":100100,"voiceFullAuto":"fullvoice/section_103204/vo_full_103204-4-42"}],"nameCenter":"Iroha","textCenter":"And we have the [textYellow:Kimochi], that made up Eve's body."},{"chara":[{"id":100100,"voiceFullAuto":"fullvoice/section_103204/vo_full_103204-4-43"}],"nameCenter":"Iroha","textCenter":"And we have userName here to be@the hub that connects everyone."},{"chara":[{"id":100100,"motion":200,"voiceFullAuto":"fullvoice/section_103204/vo_full_103204-4-44"}],"nameCenter":"Iroha","textCenter":"In other words, we've got every piece of Eve@other than the Purification System itself."},{"chara":[{"id":100100,"voiceFullAuto":"fullvoice/section_103204/vo_full_103204-4-45"}],"nameCenter":"Iroha","textCenter":"We should be far closer to Eve than Kyubey is."},{"autoTurnLast":0.2,"chara":[{"id":100100,"pos":0}],"textClear":1},{"chara":[{"id":100100,"motion":0,"voiceFullAuto":"fullvoice/section_103204/vo_full_103204-4-46"},{"cheek":0,"face":"mtn_ex_050.exp3.json","id":101500,"motion":0,"pos":2}],"nameLeft":"Iroha","textLeft":"So, Ui."},{"chara":[{"id":100100,"motion":400,"voiceFullAuto":"fullvoice/section_103204/vo_full_103204-4-47"}],"nameLeft":"Iroha","textLeft":"Try to connect with me and@the [textYellow:Kimochi] through userName."},{"chara":[{"id":100100,"voiceFullAuto":"fullvoice/section_103204/vo_full_103204-4-48"}],"nameLeft":"Iroha","textLeft":"If we all unite, and get closer to becoming Eve..."},{"chara":[{"cheek":0,"face":"mtn_ex_010.exp3.json","id":101500,"motion":100,"pos":2,"voiceFullAuto":"fullvoice/section_103204/vo_full_103204-4-49"}],"nameRight":"Ui","textRight":"Oh, we might be able to find@the new location of the core!"},{"autoTurnLast":0.2,"chara":[{"effect":"fadeout","id":100100},{"effect":"fadeout","id":101500}],"textClear":1},{"chara":[{"cheek":0,"face":"mtn_ex_040.exp3.json","id":102800,"motion":100,"pos":2,"voiceFullAuto":"fullvoice/section_103204/vo_full_103204-4-50"},{"cheek":0,"face":"mtn_ex_000.exp3.json","id":102100,"motion":0,"pos":0},{"cheek":0,"face":"mtn_ex_001.exp3.json","id":102500,"motion":0,"pos":1}],"nameRight":"Himena","textRight":"Using the [textYellow:Kimochi]'s magic is@already hella dangerous, though."},{"chara":[{"id":102800,"voiceFullAuto":"fullvoice/section_103204/vo_full_103204-4-51"}],"nameRight":"Himena","textRight":"Are you really gonna be okay connecting to it...?"},{"chara":[{"cheek":0,"face":"mtn_ex_030.exp3.json","id":102100,"motion":300,"pos":0,"voiceFullAuto":"fullvoice/section_103204/vo_full_103204-4-52"}],"nameLeft":"Yuna","textLeft":"I'm worried about the burden it will place on Ui."},{"chara":[{"cheek":0,"face":"mtn_ex_030.exp3.json","id":102500,"motion":200,"pos":1,"voiceFullAuto":"fullvoice/section_103204/vo_full_103204-4-53"}],"nameCenter":"Shizuka","textCenter":"I'm here to support her if you need it,@though I'm not sure there's much I can do..."},{"autoTurnLast":0.2,"chara":[{"effect":"fadeout","id":102800},{"effect":"fadeout","id":102500}],"textClear":1},{"autoTurnLast":0.2,"chara":[{"id":102100,"pos":2}],"textClear":1},{"chara":[{"cheek":0,"face":"mtn_ex_021.exp3.json","id":100100,"motion":200,"pos":0,"voiceFullAuto":"fullvoice/section_103204/vo_full_103204-4-54"}],"nameLeft":"Iroha","textLeft":"The [textYellow:Kimochi] and Ui were originally one being,@so they should have the best compatibility."},{"chara":[{"id":100100,"voiceFullAuto":"fullvoice/section_103204/vo_full_103204-4-55"}],"nameLeft":"Iroha","textLeft":"That's why I think it would be best for her to do@this without borrowing anyone else's strength."},{"chara":[{"id":102100,"motion":0,"voiceFullAuto":"fullvoice/section_103204/vo_full_103204-4-56"}],"nameRight":"Yuna","textRight":"As the bearer of the [textYellow:Kimochi] Stones,@Tamaki, how will this affect you?"},{"chara":[{"id":100100,"motion":100,"voiceFullAuto":"fullvoice/section_103204/vo_full_103204-4-57"}],"nameLeft":"Iroha","textLeft":"This isn't the time for us to worry@about that sort of thing."},{"chara":[{"id":100100,"voiceFullAuto":"fullvoice/section_103204/vo_full_103204-4-58"}],"nameLeft":"Iroha","textLeft":"I just have to be resolute and do this."},{"chara":[{"id":100100,"motion":400,"voiceFullAuto":"fullvoice/section_103204/vo_full_103204-4-59"}],"nameLeft":"Iroha","textLeft":"If we hesitate, everyone else will fall to despair."},{"chara":[{"id":100100,"voiceFullAuto":"fullvoice/section_103204/vo_full_103204-4-60"}],"nameLeft":"Iroha","textLeft":"Before that can happen, let's weave together hope!"},{"chara":[{"cheek":0,"face":"mtn_ex_010.exp3.json","id":102100,"voiceFullAuto":"fullvoice/section_103204/vo_full_103204-4-61"}],"nameRight":"Yuna","textRight":"Got it. I'll believe in your words."},{"autoTurnLast":0.2,"chara":[{"effect":"fadeout","id":102100}],"textClear":1},{"chara":[{"cheek":0,"face":"mtn_ex_030.exp3.json","id":100100,"motion":100,"pos":0,"voiceFullAuto":"fullvoice/section_103204/vo_full_103204-4-62"},{"cheek":0,"face":"mtn_ex_020.exp3.json","id":101500,"motion":0,"pos":2}],"nameLeft":"Iroha","textLeft":"Ready, Ui?"},{"chara":[{"cheek":0,"face":"mtn_ex_010.exp3.json","id":101500,"motion":100,"pos":2,"voiceFullAuto":"fullvoice/section_103204/vo_full_103204-4-63"}],"nameRight":"Ui","textRight":"Of course, Sis."},{"chara":[{"id":101500,"voiceFullAuto":"fullvoice/section_103204/vo_full_103204-4-64"}],"nameRight":"Ui","textRight":"We're trying to save everyone.@We can't be afraid now."},{"chara":[{"cheek":0,"face":"mtn_ex_021.exp3.json","id":100100,"motion":0,"pos":0,"voiceFullAuto":"fullvoice/section_103204/vo_full_103204-4-65"}],"nameLeft":"Iroha","textLeft":"Alright then, let's connect."},{"chara":[{"id":100100,"motion":200,"voiceFullAuto":"fullvoice/section_103204/vo_full_103204-4-66"}],"nameLeft":"Iroha","textLeft":"[textYellow:Kimochi], please do the same!"},{"chara":[{"id":100100,"voiceFullAuto":"fullvoice/section_103204/vo_full_103204-4-67"}],"nameLeft":"Iroha","textLeft":"Lend us your strength to find the core!"},{"autoTurnLast":0.01,"bgm":"stop","textClear":1},{"autoTurnLast":1.0,"bgm":"stop","chara":[{"cheek":0,"eyeClose":1,"face":"mtn_ex_021.exp3.json","id":100100,"motion":0,"pos":1}],"turnChangeIn":"whiteIn","turnChangeInTime":2.0},{"chara":[{"id":100100,"lipSynch":0,"voiceFullAuto":"fullvoice/section_103204/vo_full_103204-4-68"}],"nameCenter":"Iroha","textCenter":"...","turnChangeOut":"whiteOut"},{"autoTurnLast":0.2,"chara":[{"effect":"fadeout","id":100100}],"textClear":1},{"chara":[{"cheek":0,"face":"mtn_ex_050.exp3.json","id":102500,"motion":300,"pos":1,"voiceFullAuto":"fullvoice/section_103204/vo_full_103204-4-69"},{"cheek":0,"face":"mtn_ex_050.exp3.json","id":102100,"motion":0,"pos":0},{"cheek":0,"face":"mtn_ex_040.exp3.json","id":102800,"motion":0,"pos":2}],"nameCenter":"Shizuka","textCenter":"That's strange...@Nothing's happening...?"},{"autoTurnLast":0.2,"chara":[{"effect":"fadeout","id":102500},{"effect":"fadeout","id":102100},{"effect":"fadeout","id":102800}],"textClear":1},{"chara":[{"cheek":0,"face":"mtn_ex_052.exp3.json","id":100100,"motion":0,"pos":1,"voiceFullAuto":"fullvoice/section_103204/vo_full_103204-4-70"}],"nameCenter":"Iroha","textCenter":"Huh...? I'm not getting any@response from the [textYellow:Kimochi]..."},{"autoTurnLast":2.0,"turnChangeIn":"fadeIn"}]},"version":3}
