{"story":{"group_1":[{"autoTurnLast":0.01,"bg":"bg_adv_21171.jpg","turnChangeIn":"fadeIn"},{"nameNarration":"","narration":"[bgEffect:shakeLarge]*Clang clang clang clang clang!*","narrationEffect":"in","turnChangeOut":"fadeOut"},{"autoTurnLast":0.2,"bg":"bg_adv_21081.jpg","chara":[{"cheek":0,"face":"mtn_ex_030.exp3.json","id":103701,"motion":0,"pos":0},{"cheek":0,"face":"mtn_ex_000.exp3.json","id":103302,"motion":0,"pos":2}],"narrationEffect":"out","turnChangeIn":"fadeIn"},{"bgm":"bgm01_anime02","chara":[{"id":103701,"motion":400,"voiceFullAuto":"fullvoice/section_103201/vo_full_103201-4-2"}],"nameLeft":"Nayuta","textLeft":"It's strange. Today's a day off, but I'm up early.","turnChangeOut":"fadeOut"},{"chara":[{"eyeClose":1,"id":103701,"voiceFullAuto":"fullvoice/section_103201/vo_full_103201-4-3"}],"nameLeft":"Nayuta","textLeft":"I can still hear the sound of frying pans@echoing in my head."},{"chara":[{"id":103302,"motion":1,"voiceFullAuto":"fullvoice/section_103201/vo_full_103201-4-4"}],"nameRight":"Rabi","textRight":"You shouldn't be lazy just because it's a day off.@You should be self-disciplined instead."},{"chara":[{"id":103302,"voiceFullAuto":"fullvoice/section_103201/vo_full_103201-4-5"}],"nameRight":"Rabi","textRight":"How you spend your days off determines@your value on weekdays."},{"chara":[{"eyeClose":0,"id":103701,"motion":300,"voiceFullAuto":"fullvoice/section_103201/vo_full_103201-4-6"}],"nameLeft":"Nayuta","textLeft":"You're being awfully conscious of these things...@You're more into your work than you were before..."},{"chara":[{"cheek":0,"face":"mtn_ex_010.exp3.json","id":103302,"motion":100,"voiceFullAuto":"fullvoice/section_103201/vo_full_103201-4-7"}],"nameRight":"Rabi","textRight":"We worked hard to achieve this future,@so it's a bit exciting to finally be here."},{"chara":[{"cheek":0,"face":"mtn_ex_000.exp3.json","id":103302,"motion":0,"voiceFullAuto":"fullvoice/section_103201/vo_full_103201-4-8"}],"nameRight":"Rabi","textRight":"How does oatmeal and yogurt sound for breakfast?"},{"chara":[{"cheek":1,"eyeClose":1,"id":103701,"motion":200,"voiceFullAuto":"fullvoice/section_103201/vo_full_103201-4-9"}],"nameLeft":"Nayuta","textLeft":"*Yaaawn*"},{"chara":[{"cheek":0,"face":"mtn_ex_051.exp3.json","id":103302,"pos":2,"voiceFullAuto":"fullvoice/section_103201/vo_full_103201-4-10"},{"id":103701}],"nameRight":"Rabi","textRight":"Are you still sleepy...?"},{"chara":[{"cheek":0,"eyeClose":0,"id":103701,"motion":1,"voiceFullAuto":"fullvoice/section_103201/vo_full_103201-4-11"}],"nameLeft":"Nayuta","textLeft":"I stayed up late last night, so I can't help it."},{"chara":[{"cheek":0,"face":"mtn_ex_030.exp3.json","id":103302,"motion":100,"pos":2,"voiceFullAuto":"fullvoice/section_103201/vo_full_103201-4-12"}],"nameRight":"Rabi","textRight":"It's only natural that you'll have trouble falling@asleep after staring at your phone before bed."},{"autoTurnLast":2.0,"chara":[{"cheek":0,"face":"mtn_ex_020.exp3.json","id":103701,"motion":400,"voiceFull":"fullvoice/section_103201/vo_full_103201-4-13"}],"enableSkipAutoTurn":1,"nameLeft":"Nayuta","textLeft":"I'd rather you not assume such things of me.@Wait here a moment!"},{"chara":[{"id":103701,"motion":0}]},{"autoTurnLast":0.2,"chara":[{"effect":"fadeout","id":103701,"voiceFullStop":"fullvoice/section_103201/vo_full_103201-4-13"}],"enableSkipAutoTurn":0,"textClear":1},{"nameNarration":"","narration":"[fontSize:52]*[fontSize:50]S[fontSize:48]T[fontSize:46]O[fontSize:44]M[fontSize:42]P [fontSize:40]S[fontSize:38]T[fontSize:36]O[fontSize:34]M[fontSize:32]P [fontSize:30]S[fontSize:28]T[fontSize:26]O[fontSize:24]M[fontSize:22]P[fontSize:20]*[bgEffect:shakeLarge]","narrationBg":"","narrationEffect":"in","narrationFontSize":52.0},{"autoTurnLast":0.1,"narrationEffect":"out"},{"chara":[{"cheek":0,"face":"mtn_ex_010.exp3.json","id":103302,"motion":300,"pos":2,"voiceFullAuto":"fullvoice/section_103201/vo_full_103201-4-15"}],"nameRight":"Rabi","textRight":"Heh..."},{"nameNarration":"","narration":"[fontSize:20]*[fontSize:22]S[fontSize:24]T[fontSize:26]O[fontSize:28]M[fontSize:30]P [fontSize:32]S[fontSize:34]T[fontSize:36]O[fontSize:38]M[fontSize:40]P [fontSize:42]S[fontSize:44]T[fontSize:46]O[fontSize:48]M[fontSize:50]P[fontSize:52]*[bgEffect:shakeLarge]","narrationEffect":"in","narrationFontSize":52.0},{"autoTurnLast":0.1,"narrationEffect":"out"},{"chara":[{"cheek":0,"face":"mtn_ex_011.exp3.json","id":103701,"motion":100,"pos":0,"voiceFullAuto":"fullvoice/section_103201/vo_full_103201-4-17"}],"item":[{"path":"resource/scenario/img/part2_chapter11/103201_searchmember_badge.png","posX":0,"posY":0,"visible":"appear"}],"nameLeft":"Nayuta","textLeft":"I was making this!"},{"chara":[{"cheek":0,"face":"mtn_ex_051.exp3.json","id":103302,"motion":0,"pos":2,"voiceFullAuto":"fullvoice/section_103201/vo_full_103201-4-18"}],"nameRight":"Rabi","textRight":"Is this a badge...?"},{"chara":[{"cheek":0,"face":"mtn_ex_010.exp3.json","id":103701,"motion":1,"voiceFullAuto":"fullvoice/section_103201/vo_full_103201-4-19"}],"nameLeft":"Nayuta","textLeft":"Yes, it's like a good luck charm."},{"chara":[{"cheek":0,"face":"mtn_ex_000.exp3.json","id":103302,"motion":0,"pos":2,"voiceFullAuto":"fullvoice/section_103201/vo_full_103201-4-20"}],"nameRight":"Rabi","textRight":"It's hardened with resin, isn't it?"},{"chara":[{"id":103302,"motion":1,"voiceFullAuto":"fullvoice/section_103201/vo_full_103201-4-21"}],"nameRight":"Rabi","textRight":"Could that be us in the picture?"},{"chara":[{"id":103701,"motion":200,"voiceFullAuto":"fullvoice/section_103201/vo_full_103201-4-22"}],"nameLeft":"Nayuta","textLeft":"Yes, just so."},{"chara":[{"cheek":0,"face":"mtn_ex_011.exp3.json","id":103701,"voiceFullAuto":"fullvoice/section_103201/vo_full_103201-4-23"}],"nameLeft":"Nayuta","textLeft":"It's me, Rabi, and Mikage, the three@people in Papa's search party!"},{"chara":[{"id":103302,"motion":0,"voiceFullAuto":"fullvoice/section_103201/vo_full_103201-4-24"}],"nameRight":"Rabi","textRight":"Even though I already have a search@party badge from Mikage?"},{"chara":[{"cheek":0,"face":"mtn_ex_030.exp3.json","id":103701,"motion":400,"voiceFullAuto":"fullvoice/section_103201/vo_full_103201-4-25"}],"nameLeft":"Nayuta","textLeft":"That doesn't count.@I wanted one with all three of us on it."},{"chara":[{"id":103701,"voiceFullAuto":"fullvoice/section_103201/vo_full_103201-4-26"}],"nameLeft":"Nayuta","textLeft":"I realized something from the problems@that you and Papa are facing..."},{"chara":[{"id":103302,"voiceFullAuto":"fullvoice/section_103201/vo_full_103201-4-27"}],"nameRight":"Rabi","textRight":"...What do you mean?"},{"chara":[{"cheek":0,"face":"mtn_ex_010.exp3.json","id":103701,"motion":100,"pos":0,"voiceFullAuto":"fullvoice/section_103201/vo_full_103201-4-28"}],"nameLeft":"Nayuta","textLeft":"Actually, Rabi, both you and Papa have weak hearts."},{"chara":[{"cheek":0,"face":"mtn_ex_020.exp3.json","id":103302,"motion":200,"pos":2,"voiceFullAuto":"fullvoice/section_103201/vo_full_103201-4-29"}],"nameRight":"Rabi","textRight":"That's a bit rude, don't you think?"},{"chara":[{"id":103701,"motion":1,"pos":0,"voiceFullAuto":"fullvoice/section_103201/vo_full_103201-4-30"}],"nameLeft":"Nayuta","textLeft":"So whenever times get tough,@I want you to look at this badge"},{"chara":[{"cheek":0,"face":"mtn_ex_011.exp3.json","id":103701,"voiceFullAuto":"fullvoice/section_103201/vo_full_103201-4-31"}],"nameLeft":"Nayuta","textLeft":"and see that both Mikage and I are with you, Rabi!"},{"chara":[{"cheek":1,"face":"mtn_ex_000.exp3.json","id":103302,"motion":1,"voiceFullAuto":"fullvoice/section_103201/vo_full_103201-4-32"}],"nameRight":"Rabi","textRight":"I think we've put our resignation to rest."},{"chara":[{"id":103302,"voiceFullAuto":"fullvoice/section_103201/vo_full_103201-4-33"}],"nameRight":"Rabi","textRight":"You don't need to worry..."},{"chara":[{"cheek":0,"face":"mtn_ex_030.exp3.json","id":103701,"motion":0,"voiceFullAuto":"fullvoice/section_103201/vo_full_103201-4-34"}],"nameLeft":"Nayuta","textLeft":"But you might leave."},{"chara":[{"cheek":0,"face":"mtn_ex_051.exp3.json","id":103302,"motion":0,"voiceFullAuto":"fullvoice/section_103201/vo_full_103201-4-35"}],"nameRight":"Rabi","textRight":"...?!"},{"chara":[{"id":103701,"motion":300,"voiceFullAuto":"fullvoice/section_103201/vo_full_103201-4-36"}],"nameLeft":"Nayuta","textLeft":"Mama left. Papa left."},{"chara":[{"id":103701,"voiceFullAuto":"fullvoice/section_103201/vo_full_103201-4-37"}],"nameLeft":"Nayuta","textLeft":"Papa came back, but he said he was going to be@hospitalized."},{"chara":[{"cheek":1,"eyeClose":1,"id":103701,"voiceFullAuto":"fullvoice/section_103201/vo_full_103201-4-38"}],"nameLeft":"Nayuta","textLeft":"And if you go too, Rabi...I..."},{"autoTurnLast":0.8,"chara":[{"cheek":0,"face":"mtn_ex_030.exp3.json","id":103302,"lipSynch":0,"voiceFull":"fullvoice/section_103201/vo_full_103201-4-39"}],"nameRight":"Rabi","textRight":"......My sincere apologies."},{"chara":[{"id":103302,"lipSynch":1}]},{"chara":[{"cheek":0,"face":"mtn_ex_010.exp3.json","id":103302,"motion":100,"pos":2,"voiceFullAuto":"fullvoice/section_103201/vo_full_103201-4-40","voiceFullStop":"fullvoice/section_103201/vo_full_103201-4-39"}],"nameRight":"Rabi","textRight":"I'm very happy with the badge. I'm not@just being flattering, I really mean it."},{"chara":[{"id":103302,"motion":0,"voiceFullAuto":"fullvoice/section_103201/vo_full_103201-4-41"}],"nameRight":"Rabi","textRight":"Thank you very much."},{"chara":[{"cheek":1,"eyeClose":0,"face":"mtn_ex_010.exp3.json","id":103701,"motion":1,"voiceFullAuto":"fullvoice/section_103201/vo_full_103201-4-42"}],"nameLeft":"Nayuta","textLeft":"Yes..."},{"chara":[{"cheek":0,"face":"mtn_ex_000.exp3.json","id":103302,"motion":1,"pos":2,"voiceFullAuto":"fullvoice/section_103201/vo_full_103201-4-43"}],"nameRight":"Rabi","textRight":"However, the Professor also said that@his health is nothing to worry about."},{"chara":[{"id":103302,"voiceFullAuto":"fullvoice/section_103201/vo_full_103201-4-44"}],"nameRight":"Rabi","textRight":"He's going to the hospital today,@so let's check on him."},{"chara":[{"cheek":0,"face":"mtn_ex_030.exp3.json","id":103701,"voiceFullAuto":"fullvoice/section_103201/vo_full_103201-4-45"}],"nameLeft":"Nayuta","textLeft":"Right..."},{"nameCenter":"Mikage's Voice","textBg":"shout","textCenter":"Naaayuuutaaan!","voiceFullAuto":"fullvoice/section_103201/vo_full_103201-4-46"},{"chara":[{"cheek":0,"face":"mtn_ex_010.exp3.json","id":103302,"motion":0,"voiceFullAuto":"fullvoice/section_103201/vo_full_103201-4-47"}],"nameRight":"Rabi","textRight":"Look, Mikage is here too."},{"autoTurnLast":0.5,"textClear":1},{"autoTurnLast":1.0,"bg":"bg_adv_21691.jpg","chara":[{"cheek":0,"face":"mtn_ex_010.exp3.json","id":100201,"motion":0,"pos":0},{"cheek":0,"face":"mtn_ex_010.exp3.json","id":100101,"motion":0,"pos":2}],"turnChangeIn":"rollInLogo_Folklore"},{"chara":[{"id":100101,"motion":100,"voiceFullAuto":"fullvoice/section_103201/vo_full_103201-4-48"}],"nameRight":"Iroha","textRight":"Well then, we're off.","turnChangeOut":"rollOutLogo_Union"},{"chara":[{"id":100201,"motion":100,"voiceFullAuto":"fullvoice/section_103201/vo_full_103201-4-49"}],"nameLeft":"Yachiyo","textLeft":"I think Mifuyu will also be there@at Satomi Medical Center."},{"chara":[{"id":100101,"motion":0,"voiceFullAuto":"fullvoice/section_103201/vo_full_103201-4-50"}],"nameRight":"Iroha","textRight":"We can meet up with her there and@check in at reception together."},{"chara":[{"cheek":0,"face":"mtn_ex_030.exp3.json","id":100201,"motion":301,"voiceFullAuto":"fullvoice/section_103201/vo_full_103201-4-51"}],"nameLeft":"Yachiyo","textLeft":"I just wish we could talk with Touka and Nemu,"},{"chara":[{"id":100201,"voiceFullAuto":"fullvoice/section_103201/vo_full_103201-4-52"}],"nameLeft":"Yachiyo","textLeft":"at least through telepathy..."},{"chara":[{"id":100201,"motion":300,"voiceFullAuto":"fullvoice/section_103201/vo_full_103201-4-53"}],"nameLeft":"Yachiyo","textLeft":"Even if their bodies aren't moving, they may have@regained consciousness..."},{"chara":[{"cheek":0,"face":"mtn_ex_030.exp3.json","id":101501,"motion":300,"pos":2,"voiceFullAuto":"fullvoice/section_103201/vo_full_103201-4-54"}],"nameRight":"Ui","textRight":"Yeah."},{"chara":[{"id":101501,"voiceFullAuto":"fullvoice/section_103201/vo_full_103201-4-55"}],"nameRight":"Ui","textRight":"I heard that their bodies have healed a lot,@so I'll give it a try."},{"autoTurnLast":2.0,"turnChangeIn":"fadeIn"}]},"version":3}