{"story":{"group_1":[{"autoTurnLast":0.01,"bg":"bg_adv_19333.jpg","bgm":"bgm03_story05","turnChangeIn":"fadeIn"},{"autoTurnLast":0.5,"flashEffect":"flashWhite2","turnChangeOut":"fadeOut"},{"autoTurnLast":0.5,"item":[{"path":"resource/scenario/img/part2_chapter12/103303_witch_handmirror_gate.png","posX":0,"posY":0,"visible":"appear"}]},{"chara":[{"cheek":0,"face":"mtn_ex_011.exp3.json","id":303500,"motion":100,"pos":2,"voiceFullAuto":"fullvoice/section_103303/vo_full_103303-18-1"},{"cheek":0,"face":"mtn_ex_011.exp3.json","id":103800,"motion":1,"pos":0}],"nameRight":"Riko","textRight":"The mirror is ready!"},{"chara":[{"cheek":0,"face":"mtn_ex_020.exp3.json","id":103800,"motion":100,"voiceFullAuto":"fullvoice/section_103303/vo_full_103303-18-2"}],"nameLeft":"Mikage","textLeft":"Put your magic into it fast!@Then just picture where you wanna go!"},{"autoTurnLast":0.1,"chara":[{"effect":"fadeout","id":103800},{"effect":"fadeout","id":303500}],"item":[{"path":"resource/scenario/img/part2_chapter12/103303_witch_handmirror_gate.png","visible":"hide"}],"textClear":1},{"autoTurnLast":0.1,"bg":"bg_adv_19333.jpg","bgChangeEffect":"cameraPan"},{"autoTurnLast":1.0,"chara":[{"cheek":0,"face":"mtn_ex_010.exp3.json","id":100100,"motion":400,"pos":0,"voiceFull":"fullvoice/section_103303/vo_full_103303-18-3"},{"cheek":0,"face":"mtn_ex_100.exp3.json","id":102000,"motion":0,"pos":2}],"nameLeft":"Iroha","textLeft":"Thank you both!@Let's go, Kagome!"},{"chara":[{"cheek":0,"face":"mtn_ex_021.exp3.json","id":100100}]},{"chara":[{"id":102000,"motion":1,"voiceFullAuto":"fullvoice/section_103303/vo_full_103303-18-4","voiceFullStop":"fullvoice/section_103303/vo_full_103303-18-3"}],"nameRight":"Kagome","textRight":"Yes, I'm ready too!"},{"chara":[{"cheek":0,"face":"mtn_ex_300.exp3.json","id":102000,"lipSynch":0,"voiceFullAuto":"fullvoice/section_103303/vo_full_103303-18-5"}],"nameRight":"Aru","textRight":"<But Team Mikazuki...>"},{"chara":[{"cheek":1,"face":"mtn_ex_031.exp3.json","id":100100,"motion":301,"pos":0,"voiceFullAuto":"fullvoice/section_103303/vo_full_103303-18-6"}],"nameLeft":"Iroha","textLeft":"...Yeah. They're still fighting for us.@But I don't think they'll last long."},{"chara":[{"cheek":1,"face":"mtn_ex_021.exp3.json","id":100100,"voiceFullAuto":"fullvoice/section_103303/vo_full_103303-18-7"}],"nameLeft":"Iroha","textLeft":"So to ensure the that feelings they@entrusted to me don't go to waste...!"},{"autoTurnLast":0.1,"chara":[{"effect":"fadeout","id":100100},{"effect":"fadeout","id":102000}],"textClear":1},{"autoTurnLast":0.01,"bg":"bg_adv_19333.jpg","bgChangeEffect":"cameraPan"},{"autoTurnLast":0.5,"item":[{"path":"resource/scenario/img/part2_chapter12/103303_witch_handmirror_gate.png","posX":0,"posY":0,"visible":"appear"}]},{"chara":[{"cheek":0,"face":"mtn_ex_021.exp3.json","id":100100,"motion":200,"pos":0,"voiceFullAuto":"fullvoice/section_103303/vo_full_103303-18-8"},{"cheek":0,"face":"mtn_ex_100.exp3.json","id":102000,"motion":0,"pos":2}],"nameLeft":"Iroha","textLeft":"I will bring Ui and userName here from the past!"},{"autoTurnLast":2.0,"bgm":"stop","flashEffect":"flashWhiteSlow2","textClear":1},{"chara":[{"cheek":0,"face":"mtn_ex_050.exp3.json","id":100100,"motion":400,"voiceFullAuto":"fullvoice/section_103303/vo_full_103303-18-9"}],"nameLeft":"Iroha","textLeft":"[chara:100100:effect_emotion_surprise_0][se:7226_shock]...?!"},{"chara":[{"id":100100,"voiceFullAuto":"fullvoice/section_103303/vo_full_103303-18-10"}],"nameLeft":"Iroha","textLeft":"Touka, Nemu... I'm feeling a reaction@from their Soul Gems..."},{"chara":[{"cheek":0,"face":"mtn_ex_150.exp3.json","id":102000,"motion":100,"pos":2,"voiceFullAuto":"fullvoice/section_103303/vo_full_103303-18-11"}],"nameRight":"Kagome","textRight":"They're reacting on their own?"},{"chara":[{"cheek":0,"face":"mtn_ex_030.exp3.json","id":100100,"motion":300,"pos":0,"voiceFullAuto":"fullvoice/section_103303/vo_full_103303-18-12"}],"nameLeft":"Iroha","textLeft":"Yeah, it's like they're trying to get my attention..."},{"chara":[{"cheek":0,"eyeClose":1,"face":"mtn_ex_060.exp3.json","id":100100,"motion":401,"voiceFullAuto":"fullvoice/section_103303/vo_full_103303-18-13"}],"nameLeft":"Iroha","textLeft":"[flashEffect:flashWhite2]Kyaaah!"},{"autoTurnLast":0.5,"bg":"bg_adv_21251.jpg","chara":[{"cheek":1,"face":"mtn_ex_050.exp3.json","id":100100,"motion":0,"pos":1}],"turnChangeIn":"whiteIn"},{"bgm":"bgm21_system02","chara":[{"id":100100,"voiceFullAuto":"fullvoice/section_103303/vo_full_103303-18-14"}],"nameCenter":"Iroha","textCenter":"Tou...ka...@Nemu...","turnChangeOut":"whiteOut"},{"autoTurnLast":0.2,"chara":[{"effect":"fadeout","id":100100}],"textClear":1},{"chara":[{"cheek":0,"face":"mtn_ex_030.exp3.json","id":100700,"motion":400,"pos":0,"voiceFullAuto":"fullvoice/section_103303/vo_full_103303-18-15"},{"cheek":0,"face":"mtn_ex_030.exp3.json","id":101400,"motion":0,"pos":2}],"nameLeft":"Touka","textLeft":"We've been trying to reach you for a long time,@but nothing worked."},{"chara":[{"id":100700,"voiceFullAuto":"fullvoice/section_103303/vo_full_103303-18-16"}],"nameLeft":"Touka","textLeft":"I was wondering what to do..."},{"chara":[{"id":101400,"motion":300,"voiceFullAuto":"fullvoice/section_103303/vo_full_103303-18-17"}],"nameRight":"Nemu","textRight":"I think it would have been impossible were it not@for the [textYellow:Kimochi] Stones allowing a connection."},{"chara":[{"cheek":1,"face":"mtn_ex_050.exp3.json","id":100100,"motion":0,"pos":0,"voiceFullAuto":"fullvoice/section_103303/vo_full_103303-18-18"}],"nameLeft":"Iroha","textLeft":"Are you two okay...?"},{"chara":[{"cheek":1,"face":"mtn_ex_010.exp3.json","id":100100,"motion":400,"pos":0,"voiceFullAuto":"fullvoice/section_103303/vo_full_103303-18-19"}],"nameLeft":"Iroha","textLeft":"Did the plan actually work, maybe...?"},{"chara":[{"cheek":0,"face":"mtn_ex_030.exp3.json","id":100700,"motion":300,"pos":2,"voiceFullAuto":"fullvoice/section_103303/vo_full_103303-18-20"}],"nameRight":"Touka","textRight":"No, you were right. It failed the moment we lost Ui."},{"autoTurnLast":0.2,"chara":[{"cheek":0,"face":"mtn_ex_030.exp3.json","id":100100,"lipSynch":0,"motion":300,"pos":0,"voiceFull":"fullvoice/section_103303/vo_full_103303-18-21"}],"nameLeft":"Iroha","textLeft":"...I knew it."},{"chara":[{"id":100100,"lipSynch":1}]},{"chara":[{"cheek":0,"face":"mtn_ex_000.exp3.json","id":101400,"motion":0,"pos":2,"voiceFullAuto":"fullvoice/section_103303/vo_full_103303-18-22","voiceFullStop":"fullvoice/section_103303/vo_full_103303-18-21"}],"nameRight":"Nemu","textRight":"We had been desperately trying to@communicate with you, Big Sister."},{"chara":[{"id":101400,"voiceFullAuto":"fullvoice/section_103303/vo_full_103303-18-23"}],"nameRight":"Nemu","textRight":"There's something crucial we must impart."},{"chara":[{"cheek":0,"face":"mtn_ex_050.exp3.json","id":100100,"motion":0,"pos":0,"voiceFullAuto":"fullvoice/section_103303/vo_full_103303-18-24"}],"nameLeft":"Iroha","textLeft":"Something crucial...?"},{"chara":[{"cheek":0,"face":"mtn_ex_030.exp3.json","id":101400,"motion":200,"pos":2,"voiceFullAuto":"fullvoice/section_103303/vo_full_103303-18-25"}],"nameRight":"Nemu","textRight":"Indeed..."},{"chara":[{"id":101400,"voiceFullAuto":"fullvoice/section_103303/vo_full_103303-18-26"}],"nameRight":"Nemu","textRight":"If you were to connect to the past@and bring back Ui and userName..."},{"chara":[{"id":101400,"voiceFullAuto":"fullvoice/section_103303/vo_full_103303-18-27"}],"nameRight":"Nemu","textRight":"There is no doubt that the@entire world would collapse."},{"chara":[{"cheek":0,"face":"mtn_ex_052.exp3.json","id":100100,"motion":401,"voiceFullAuto":"fullvoice/section_103303/vo_full_103303-18-28"}],"nameLeft":"Iroha","textLeft":"Eh...? You're joking, right...?@How can that be...?!"},{"chara":[{"cheek":0,"face":"mtn_ex_001.exp3.json","id":100700,"motion":1,"pos":2,"voiceFullAuto":"fullvoice/section_103303/vo_full_103303-18-29"}],"nameRight":"Touka","textRight":"Doing so would mean Ui would be nonexistent@from the point she was taken until now."},{"chara":[{"id":100700,"voiceFullAuto":"fullvoice/section_103303/vo_full_103303-18-30"}],"nameRight":"Touka","textRight":"It would create a mysterious phenomenon@akin to the Grandfather Paradox."},{"chara":[{"id":100700,"motion":100,"voiceFullAuto":"fullvoice/section_103303/vo_full_103303-18-31"},{"id":100100,"motion":0}],"nameRight":"Touka","textRight":"Simply put, if Ui does not exist@during that period in the past,"},{"chara":[{"id":100700,"voiceFullAuto":"fullvoice/section_103303/vo_full_103303-18-32"}],"nameRight":"Touka","textRight":"this situation now in which we're communicating@would not come to exist."},{"chara":[{"cheek":0,"face":"mtn_ex_030.exp3.json","id":100700,"motion":400,"voiceFullAuto":"fullvoice/section_103303/vo_full_103303-18-33"}],"nameRight":"Touka","textRight":"The future would be entirely different..."},{"chara":[{"id":100700,"voiceFullAuto":"fullvoice/section_103303/vo_full_103303-18-34"}],"nameRight":"Touka","textRight":"And it would also mean that the act of bringing Ui@to this point would never have occurred either."},{"chara":[{"id":100700,"motion":201,"voiceFullAuto":"fullvoice/section_103303/vo_full_103303-18-35"}],"nameRight":"Touka","textRight":"Simply put, the Ui of the past would simply@and inexplicably cease to exist."},{"chara":[{"id":100700,"motion":300,"voiceFullAuto":"fullvoice/section_103303/vo_full_103303-18-36"}],"nameRight":"Touka","textRight":"And without Ui, Magical Girls@can no longer be saved..."},{"chara":[{"cheek":0,"face":"mtn_ex_021.exp3.json","id":100100,"motion":200,"pos":0,"voiceFullAuto":"fullvoice/section_103303/vo_full_103303-18-37"}],"nameLeft":"Iroha","textLeft":"S-so then...if I were to tell myself@in the past about what happened..."},{"chara":[{"id":100100,"voiceFullAuto":"fullvoice/section_103303/vo_full_103303-18-38"}],"nameLeft":"Iroha","textLeft":"Then we would be able to avoid Ui's death, right?!"},{"chara":[{"cheek":0,"face":"mtn_ex_000.exp3.json","id":101400,"motion":100,"pos":2,"voiceFullAuto":"fullvoice/section_103303/vo_full_103303-18-39"}],"nameRight":"Nemu","textRight":"It's certainly a possibility. But I'm arrested@by the theory Touka has presented."},{"chara":[{"id":101400,"motion":300,"voiceFullAuto":"fullvoice/section_103303/vo_full_103303-18-40"},{"id":100100,"motion":0}],"nameRight":"Nemu","textRight":"If the you of the past learns of the future@and changes its course so Ui survives,"},{"chara":[{"id":101400,"voiceFullAuto":"fullvoice/section_103303/vo_full_103303-18-41"}],"nameRight":"Nemu","textRight":"then this action of you conveying@this knowledge to the past..."},{"chara":[{"id":101400,"voiceFullAuto":"fullvoice/section_103303/vo_full_103303-18-42"}],"nameRight":"Nemu","textRight":"It would not have come to pass either."},{"chara":[{"id":101400,"motion":0,"voiceFullAuto":"fullvoice/section_103303/vo_full_103303-18-43"}],"nameRight":"Nemu","textRight":"Put another way, you would have learned this@information without anyone having told you."},{"chara":[{"id":101400,"voiceFullAuto":"fullvoice/section_103303/vo_full_103303-18-44"}],"nameRight":"Nemu","textRight":"If that contradiction were to be created..."},{"chara":[{"cheek":0,"face":"mtn_ex_030.exp3.json","id":100100,"motion":300,"pos":0,"voiceFullAuto":"fullvoice/section_103303/vo_full_103303-18-45"}],"nameLeft":"Iroha","textLeft":"Then that would mean..."},{"chara":[{"cheek":0,"face":"mtn_ex_030.exp3.json","id":101400,"motion":200,"pos":2,"voiceFullAuto":"fullvoice/section_103303/vo_full_103303-18-46"}],"nameRight":"Nemu","textRight":"We are in checkmate."},{"chara":[{"cheek":1,"face":"mtn_ex_031.exp3.json","id":100100,"lipSynch":0,"voiceFullAuto":"fullvoice/section_103303/vo_full_103303-18-47"}],"nameLeft":"Iroha","textLeft":"..."},{"chara":[{"cheek":0,"face":"mtn_ex_030.exp3.json","id":100700,"motion":1,"pos":2,"voiceFullAuto":"fullvoice/section_103303/vo_full_103303-18-48"}],"nameRight":"Touka","textRight":"If the theory of parallel worlds is true,@then our chances go up from zero, but..."},{"chara":[{"id":100700,"voiceFullAuto":"fullvoice/section_103303/vo_full_103303-18-49"}],"nameRight":"Touka","textRight":"Those who would be saved would be of a different@world branching from our changed actions."},{"chara":[{"id":100700,"voiceFullAuto":"fullvoice/section_103303/vo_full_103303-18-50"}],"nameRight":"Touka","textRight":"We who live in this timeline would be doomed."},{"chara":[{"cheek":0,"face":"mtn_ex_021.exp3.json","id":100100,"motion":0,"pos":0,"voiceFullAuto":"fullvoice/section_103303/vo_full_103303-18-51"}],"nameLeft":"Iroha","textLeft":"So while it's a long shot, we have a chance...?"},{"chara":[{"cheek":0,"face":"mtn_ex_001.exp3.json","id":100700,"motion":400,"pos":2,"voiceFullAuto":"fullvoice/section_103303/vo_full_103303-18-52"}],"nameRight":"Touka","textRight":"If the parallel world theory isn't in play, then@you might destroy the universe outright."},{"chara":[{"eyeClose":1,"id":100100,"motion":301,"voiceFullAuto":"fullvoice/section_103303/vo_full_103303-18-53"}],"nameLeft":"Iroha","textLeft":"But still...if there's a possibility..."},{"chara":[{"cheek":0,"face":"mtn_ex_000.exp3.json","id":101400,"motion":100,"pos":2,"voiceFullAuto":"fullvoice/section_103303/vo_full_103303-18-54"}],"nameRight":"Nemu","textRight":"You're giving it a try?"},{"chara":[{"eyeClose":0,"id":100100,"motion":100,"voiceFullAuto":"fullvoice/section_103303/vo_full_103303-18-55"}],"nameLeft":"Iroha","textLeft":"Yeah... I'll take the gamble on there being@another world where we can be saved."},{"autoTurnLast":2.0,"turnChangeIn":"fadeIn"}]},"version":3}