{"story":{"group_1":[{"armatureList":[{"animation":["action"],"armatureId":1,"filePath":"resource/image_native/effect/story/general/3003_act_picture.ExportJson","zOrder":"messageBack"}],"autoTurnLast":0.2,"bg":"bg_adv_21702.jpg","chara":[{"cheek":0,"face":"mtn_ex_020.exp3.json","id":112102,"motion":0,"pos":2},{"cheek":0,"face":"mtn_ex_020.exp3.json","id":112101,"motion":0,"pos":0}],"turnChangeIn":"fadeIn"},{"autoTurnLast":0.2,"turnChangeOut":"fadeOut"},{"chara":[{"id":112102,"motion":100}],"nameRight":"Juri","textRight":"...Alright, let's do this!"},{"chara":[{"id":112101}],"nameLeft":"Yuna","textLeft":"...Let's."},{"chara":[{"id":112102,"motion":400,"mouthOpen":1}],"nameRight":"Juri","textBg":"shout","textRight":"[flashEffect:flashWhite2][surround:1121A01]URAAAAAAAH!"},{"chara":[{"id":112101,"motion":400,"mouthOpen":1},{"id":112102,"mouthOpen":0}],"nameLeft":"Yuna","textBg":"shout","textLeft":"[flashEffect:flashWhite2][surround:1121A07]HAAAAAAAH!"},{"autoTurnLast":0.2,"chara":[{"id":112101,"mouthOpen":0}],"textClear":1},{"autoTurnLast":2.0,"bg":"bg_adv_21251.jpg","chara":[{"cheek":0,"face":"mtn_ex_050.exp3.json","id":103601,"motion":0,"pos":1}],"deleteArmatureList":[1],"turnChangeIn":"whiteIn","turnChangeInTime":1.5},{"bgm":"bgm23_folklore05","chara":[{"id":103601}],"nameCenter":"Urara","textCenter":"...Say, what the heck is going on?","turnChangeOut":"whiteOut"},{"chara":[{"id":103601}],"nameCenter":"Urara","textCenter":"Why'd Yuna and Juri do that...?"},{"autoTurnLast":0.2,"chara":[{"effect":"fadeout","id":103601}],"textClear":1},{"chara":[{"cheek":0,"face":"mtn_ex_030.exp3.json","id":103401,"motion":0,"pos":2},{"cheek":0,"face":"mtn_ex_030.exp3.json","id":103301,"motion":0,"pos":0}],"nameNarration":"Rabi","narration":"We awoke in a strange space, watching Kureha and@Ooba on some sort of monitor.","narrationBg":"","narrationEffect":"in"},{"narration":"It was terrible,@the way they swung their weapons at the dead–@the very image of a demon...@I couldn't fathom what they were trying to do."},{"chara":[{"id":103401,"motion":300}],"nameRight":"Asahi","narrationEffect":"out","textRight":"We can't hear them talking, so their motives@are unclear..."},{"chara":[{"id":103301,"motion":300}],"nameLeft":"Rabi","textLeft":"I could understand if they'd done this in the past,@but it's not like them to suddenly lash out..."},{"chara":[{"cheek":0,"face":"mtn_ex_030.exp3.json","id":103601,"motion":200,"pos":0}],"nameLeft":"Urara","textLeft":"Yuna and Juri are real kind, see,@so there's gotta be a reason...!"},{"chara":[{"cheek":0,"face":"mtn_ex_030.exp3.json","id":103401,"motion":1,"pos":2}],"nameRight":"Asahi","textRight":"If that is the case, perhaps they're being@manipulated...? Or something to that effect."},{"chara":[{"cheek":0,"face":"mtn_ex_000.exp3.json","id":103301,"motion":1,"pos":2}],"nameRight":"Rabi","textRight":"By the way, Urara, do you know any of those, er―@I think they're ghosts?"},{"chara":[{"id":103601,"motion":300}],"nameLeft":"Urara","textLeft":"I can't see their faces, so I dunno..."},{"chara":[{"id":103601}],"nameLeft":"Urara","textLeft":"...But it sure seems like there are a bunch@of dead people."},{"chara":[{"eyeClose":1,"id":103601}],"nameLeft":"Urara","textLeft":"...Why isn't Sakuya there...?"},{"chara":[{"cheek":0,"face":"mtn_ex_030.exp3.json","id":103401,"lipSynch":0,"motion":0,"pos":2}],"nameRight":"Asahi","textRight":"..."},{"chara":[{"cheek":0,"face":"mtn_ex_030.exp3.json","id":103301,"motion":300,"pos":0}],"nameLeft":"Rabi","textLeft":"To backtrack, what even is this space...?"},{"chara":[{"id":103401,"motion":300}],"nameRight":"Asahi","textRight":"About that..."},{"chara":[{"id":103401}],"nameRight":"Asahi","textRight":"When I activated my magic, I had the sensation of@my power getting stolen away..."},{"chara":[{"cheek":0,"face":"mtn_ex_050.exp3.json","id":103601,"motion":0,"pos":0}],"nameLeft":"Urara","textLeft":"...So basically, you used up all your juice, and..."},{"chara":[{"cheek":0,"face":"mtn_ex_051.exp3.json","id":103301,"lipSynch":0,"motion":0,"pos":2}],"nameRight":"Rabi","textRight":"...[wait:1.2][chara:103301:cheek_0][chara:103301:lipSynch_1]We all died?"},{"chara":[{"id":103601,"motion":400}],"nameLeft":"Urara","textLeft":"There's definitely ghosts, so... Is this the afterlife?! "},{"chara":[{"id":103301,"motion":100}],"nameRight":"Rabi","textRight":"...I've always been a little curious if such a@thing existed, but..."},{"chara":[{"cheek":0,"face":"mtn_ex_030.exp3.json","id":103401,"motion":1,"pos":2}],"nameRight":"Asahi","textRight":"If I were to come up with the worst-case scenario..."},{"chara":[{"id":103401}],"nameRight":"Asahi","textRight":"I'd say...my Soul Gem has blackened, and this is@my Witch's Labyrinth."},{"chara":[{"id":103601,"motion":100}],"nameLeft":"Urara","textLeft":"W-we're all toast, see~!"},{"bgm":"stop","chara":[{"cheek":0,"face":"mtn_ex_051.exp3.json","id":103301,"motion":0,"pos":0},{"cheek":0,"face":"mtn_ex_010.exp3.json","id":800200,"motion":0,"pos":2}],"nameNarration":"???'s Voice","narration":"\"Don't worry.\"","narrationBg":"bg_adv_21251.jpg","narrationEffect":"in"},{"narration":"\"It's true that your magic@has been taken away, but you're not dead.@You haven't turned into Witches, either.\""},{"bgm":"bgm03_story06","chara":[{"id":103301}],"nameLeft":"Rabi","narrationEffect":"out","textLeft":"...And you are?"},{"chara":[{"cheek":0,"face":"mtn_ex_050.exp3.json","id":800200,"pos":2}],"nameRight":"???","textRight":"Oh, um... I'm an acquaintance of Juri and@her friend, or something."},{"chara":[{"id":800200}],"nameRight":"Guide","textRight":"Mm... I guess you could call me your guide?"},{"chara":[{"cheek":0,"face":"mtn_ex_050.exp3.json","id":103401,"motion":1,"pos":0}],"nameLeft":"Asahi","textLeft":"...Why did you phrase that as a question?"},{"chara":[{"cheek":0,"face":"mtn_ex_030.exp3.json","id":800200,"pos":2}],"nameRight":"Guide","textRight":"S-sorry..."},{"chara":[{"cheek":0,"face":"mtn_ex_010.exp3.json","id":800200,"pos":2}],"nameRight":"Guide","textRight":"I can tell you about this place, though."},{"chara":[{"cheek":0,"face":"mtn_ex_010.exp3.json","id":103601,"motion":100,"pos":0}],"nameLeft":"Urara","textLeft":"Please do!"},{"chara":[{"id":800200}],"nameRight":"Guide","textRight":"Alright! Let me think, uh...@Where to start..."},{"chara":[{"id":800200},{"cheek":0,"face":"mtn_ex_050.exp3.json","id":103401,"motion":0,"pos":0}],"nameRight":"Guide","textRight":"Miu...ra, this is a space made using your magic..."},{"chara":[{"id":103401}],"nameLeft":"Asahi","textLeft":"...Have I told you my name?"},{"chara":[{"id":800200}],"nameRight":"Guide","textRight":"Ah, ehehe...um..."},{"chara":[{"id":800200}],"nameRight":"Guide","textRight":"At the moment, Aleksha Kurusu...[chara:800200:lipSynch_0][wait:0.8][chara:800200:cheek_1][chara:800200:face_mtn_ex_030.exp3.json][chara:800200:lipSynch_1] Kurusu is@purifying your Soul Gems from outside."},{"chara":[{"cheek":0,"face":"mtn_ex_030.exp3.json","id":103301,"motion":0,"pos":0}],"nameLeft":"Rabi","textLeft":"...Are you reading off of a script?"},{"chara":[{"cheek":0,"eyeClose":1,"face":"mtn_ex_010.exp3.json","id":103401,"motion":0,"pos":0}],"nameLeft":"Asahi","textLeft":"I suppose \"Alexandra\" could be hard to pronounce@if you've never said it before."},{"chara":[{"cheek":0,"id":800200,"pos":2}],"nameRight":"Guide","textRight":"Urgh... I swear I'm not up to anything shady..."},{"chara":[{"cheek":0,"face":"mtn_ex_000.exp3.json","id":103301,"motion":100,"pos":0}],"nameLeft":"Rabi","textLeft":"Well... Suspicious or not, you're the only person@we can rely on right now."},{"chara":[{"id":103301}],"nameLeft":"Rabi","textLeft":"Could you please continue?"},{"autoTurnLast":2.0,"turnChangeIn":"fadeIn"}]},"version":3}